BlockLoggingInator-1.0.6.dist-info/DESCRIPTION.rst
BlockLoggingInator-1.0.6.dist-info/METADATA
BlockLoggingInator-1.0.6.dist-info/RECORD
BlockLoggingInator-1.0.6.dist-info/WHEEL
BlockLoggingInator-1.0.6.dist-info/metadata.json
BlockLoggingInator-1.0.6.dist-info/top_level.txt
blocklogginginator/__init__.py
local/__init__.py
