Metadata-Version: 2.0
Name: BlockLoggingInator
Version: 1.0.6
Summary: A silly class to logging blocks execution time.
Home-page: https://bitbucket.org/ellethee/blocklogginginator/overview
Author: ellethee
Author-email: luca800@gmail.com
License: MIT
Keywords: simple logging blocks execution time executiontime test
Platform: UNKNOWN
Classifier: Development Status :: 5 - Production/Stable
Classifier: Intended Audience :: Developers
Classifier: Topic :: Software Development :: Testing
Classifier: License :: OSI Approved :: MIT License
Classifier: Programming Language :: Python :: 2
Classifier: Programming Language :: Python :: 3
